MANIFEST.in
README.rst
setup.py
django_ide.egg-info/PKG-INFO
django_ide.egg-info/SOURCES.txt
django_ide.egg-info/dependency_links.txt
django_ide.egg-info/not-zip-safe
django_ide.egg-info/top_level.txt
djide/__init__.py
djide/models.py
djide/tests.py
djide/urls.py
djide/views.py
djide/whooshlib.py
djide/metafiles/.django
djide/metafiles/.djide
djide/metafiles/.htmlide
djide/static/codemirror/LICENSE
djide/static/codemirror/codemirror.js
djide/static/codemirror/codemirror_all.js
djide/static/codemirror/csscolors_on_white.css
djide/static/codemirror/editor.js
djide/static/codemirror/highlight.js
djide/static/codemirror/jscolors_on_white.css
djide/static/codemirror/parsecss.js
djide/static/codemirror/parsedummy.js
djide/static/codemirror/parsehtmlmixed.js
djide/static/codemirror/parsejavascript.js
djide/static/codemirror/parsejavascript.js_PLAYGROUND
djide/static/codemirror/parsepython.js
djide/static/codemirror/parsesparql.js
djide/static/codemirror/parsexml.js
djide/static/codemirror/pythoncolors.css
djide/static/codemirror/select.js
djide/static/codemirror/stringstream.js
djide/static/codemirror/styles.css
djide/static/codemirror/tokenize.js
djide/static/codemirror/tokenizejavascript.js
djide/static/codemirror/undo.js
djide/static/codemirror/util.js
djide/static/codemirror/xmlcolors_on_white.css
djide/static/css/menus.css
djide/static/css/ui-ide.css
djide/static/extjs/ext-all.js
djide/static/extjs/adapter/ext/ext-base-debug-w-comments.js
djide/static/extjs/adapter/ext/ext-base-debug.js
djide/static/extjs/adapter/ext/ext-base.js
djide/static/extjs/adapter/jquery/ext-jquery-adapter-debug.js
djide/static/extjs/adapter/jquery/ext-jquery-adapter.js
djide/static/extjs/adapter/prototype/ext-prototype-adapter-debug.js
djide/static/extjs/adapter/prototype/ext-prototype-adapter.js
djide/static/extjs/adapter/yui/ext-yui-adapter-debug.js
djide/static/extjs/adapter/yui/ext-yui-adapter.js
djide/static/extjs/resources/charts.swf
djide/static/extjs/resources/expressinstall.swf
djide/static/extjs/resources/resources.jsb
djide/static/extjs/resources/css/README.txt
djide/static/extjs/resources/css/debug.css
