Metadata-Version: 1.0
Name: django-ide
Version: 0.0.5
Summary: Web based IDE to develop Django apps
Home-page: http://github.com/lusob/django-ide
Author: Luis Sobrecueva
Author-email: luis@sobrecueva.com
License: GPL
Download-URL: http://github.com/lusob/django-ide/downloads
Keywords: IDE,Integrated Development Environment,Django IDE
Platform: UNKNOWN
Classifier: Programming Language :: Python
Classifier: Programming Language :: JavaScript
Classifier: Development Status :: 2 - Pre-Alpha
Classifier: Environment :: Web Environment
Classifier: Framework :: Django
Classifier: Intended Audience :: Developers
Classifier: License :: OSI Approved :: GNU General Public License (GPL)
Classifier: Natural Language :: English
Classifier: Operating System :: OS Independent
Classifier: Topic :: Text Editors :: Integrated Development Environments (IDE)
